Workbook

Sheet SFY2025 Budget Reference
A1: Vermont Medicaid SFY2025 — Budgeted PMPM Reference Data
A2: Source: DVHA Budget Book SFY2026 (As Passed budget, retroactively reported) | Prepared by: Graham Pinti
A3: NOTE: SFY2025 "As Passed" figures were not published as a standalone PMPM Legislative Report (that report series ended after SFY2022). These figures are sourced from the DVHA Annual Report and Budget Book SFY2026, which retroactively reports the prior year's As Passed budget alongside SFY2026 projections. All figures reflect DVHA-only scope. Choices for Care no longer exists as a standalone MEG as of the 1115 waiver change; its costs are now distributed across other eligibility groups. Dr. D Expansion (IHIP) is a new MEG that began July 1, 2022.
A4: Medicaid Eligibility Group (MEG) | B4: Avg Monthly Enrollment | C4: Gross PMPM ($) | D4: Premium PMPM ($) | E4: Net PMPM ($) | F4: Annual Budget Est. ($)
A5: ABD Adult | B5: 8005 | C5: 846.95 | D5: 0 | E5: =C5-D5 -> 846.95 | F5: =B5*C5*12 -> 81358017
A6: Dual Eligible | B6: 22380 | C6: 366.71 | D6: 0 | E6: =C6-D6 -> 366.71 | F6: =B6*C6*12 -> 98483638
A7: General Adult | B7: 15000 | C7: 415.86 | D7: 0 | E7: =C7-D7 -> 415.86 | F7: =B7*C7*12 -> 74854800
A8: New Adult Childless | B8: 38000 | C8: 491.19 | D8: 0 | E8: =C8-D8 -> 491.19 | F8: =B8*C8*12 -> 223982640
A9: New Adult w/Child | B9: 22500 | C9: 450.49 | D9: 0 | E9: =C9-D9 -> 450.49 | F9: =B9*C9*12 -> 121632300
A10: BD Child | B10: 1800 | C10: 1129.82 | D10: 0 | E10: =C10-D10 -> 1129.82 | F10: =B10*C10*12 -> 24404112
A11: General Child | B11: 58480 | C11: 285.39 | D11: 0 | E11: =C11-D11 -> 285.39 | F11: =B11*C11*12 -> 2.0027529e+08
A12: CHIP | B12: 4411 | C12: 184.55 | D12: 0 | E12: =C12-D12 -> 184.55 | F12: =B12*C12*12 -> 9768600.6
A13: Dr. D Expansion (IHIP) | B13: 252 | C13: 400 | D13: 0 | E13: =C13-D13 -> 400 | F13: =B13*C13*12 -> 1209600
A14: Pharmacy Only | B14: 9763 | C14: 66.85 | D14: 0 | E14: =C14-D14 -> 66.85 | F14: =B14*C14*12 -> 7831878.6
A15: Vermont Premium Assist. | B15: 14165 | C15: 31.85 | D15: 0 | E15: =C15-D15 -> 31.85 | F15: =B15*C15*12 -> 5413863
A16: Vermont Cost Sharing | B16: 4995 | C16: 30.98 | D16: 0 | E16: =C16-D16 -> 30.98 | F16: =B16*C16*12 -> 1856941.2
A17: TOTAL / WEIGHTED AVG | B17: =SUM(B5:B16) -> 199751 | C17: =SUMPRODUCT(B5:B16,C5:C16)/SUM(B5:B16) -> 355.05524 | D17: — | E17: =SUMPRODUCT(B5:B16,E5:E16)/SUM(B5:B16) -> 355.05524 | F17: =SUM(F5:F16) -> 8.5107168e+08
A18: Note: Enrollment and Annual Budget are totals (summed). PMPM figures are enrollment-weighted averages, not simple averages.

Sheet Reconciliation Report
A1: Vermont Medicaid SFY2025 — Budget vs. Actual PMPM Reconciliation (Recalibrated Thresholds)
A2: Prepared by: Graham Pinti | Recalibrated Threshold: Monitor >6.3% enroll/8.9% PMPM, Escalate >9.5%/13.4% (1/1.5 historical stdev)
A3: RECONCILIATION PROCESS: Budgeted figures sourced from the DVHA Annual Report and Budget Book SFY2026 (SFY2025 "As Passed" column, DVHA-only scope). Actual figures sourced from the DVHA Medicaid Program Enrollment & Expenditures Quarterly Report, Q4 SFY25 YTD (DVHA-only scope, period ending June 30, 2025). Thresholds matched to the recalibrated SFY2022 methodology for direct year-over-year comparability. Pharmacy Only shows an unusually large PMPM variance inconsistent with the Budget Book's own BAA/Gov. Rec. trendline for VPharm; the most likely explanation is a gross-vs-net (rebate-adjusted) reporting difference, though this could not be confirmed from public data. Choices for Care no longer exists as a standalone MEG as of the 1115 waiver change.
A4: MEG | B4: Budget Enrollment | C4: Actual Enrollment | D4: Enroll. Variance | E4: Enroll. Var % | F4: Budget PMPM ($) | G4: Actual PMPM ($) | H4: PMPM Variance ($) | I4: PMPM Var % | J4: Budget Ann. Cost ($) | K4: Actual Ann. Cost ($) | L4: Cost Impact ($)
A5: ABD Adult | B5: 8005 | C5: 7402 | D5: =C5-B5 -> -603 | E5: =D5/B5 -> -0.07532792 | F5: 846.95 | G5: 1171.49 | H5: =G5-F5 -> 324.54 | I5: =H5/F5 -> 0.38318673 | J5: =B5*F5*12 -> 81358017 | K5: =C5*G5*12 -> 1.0405643e+08 | L5: =K5-J5 -> 22698411
A6: Dual Eligible | B6: 22380 | C6: 21991 | D6: =C6-B6 -> -389 | E6: =D6/B6 -> -0.017381591 | F6: 366.71 | G6: 440.44 | H6: =G6-F6 -> 73.73 | I6: =H6/F6 -> 0.20105806 | J6: =B6*F6*12 -> 98483638 | K6: =C6*G6*12 -> 1.1622859e+08 | L6: =K6-J6 -> 17744955
A7: General Adult | B7: 15000 | C7: 12351 | D7: =C7-B7 -> -2649 | E7: =D7/B7 -> -0.1766 | F7: 415.86 | G7: 568.79 | H7: =G7-F7 -> 152.93 | I7: =H7/F7 -> 0.36774395 | J7: =B7*F7*12 -> 74854800 | K7: =C7*G7*12 -> 84301503 | L7: =K7-J7 -> 9446703.5
A8: New Adult Childless | B8: 38000 | C8: 35417 | D8: =C8-B8 -> -2583 | E8: =D8/B8 -> -0.067973684 | F8: 491.19 | G8: 584.85 | H8: =G8-F8 -> 93.66 | I8: =H8/F8 -> 0.19067978 | J8: =B8*F8*12 -> 223982640 | K8: =C8*G8*12 -> 2.4856359e+08 | L8: =K8-J8 -> 24580949
A9: New Adult w/Child | B9: 22500 | C9: 21348 | D9: =C9-B9 -> -1152 | E9: =D9/B9 -> -0.0512 | F9: 450.49 | G9: 522.94 | H9: =G9-F9 -> 72.45 | I9: =H9/F9 -> 0.16082488 | J9: =B9*F9*12 -> 121632300 | K9: =C9*G9*12 -> 1.3396468e+08 | L9: =K9-J9 -> 12332377
A10: BD Child | B10: 1800 | C10: 1928 | D10: =C10-B10 -> 128 | E10: =D10/B10 -> 0.071111111 | F10: 1129.82 | G10: 1326.1 | H10: =G10-F10 -> 196.28 | I10: =H10/F10 -> 0.17372679 | J10: =B10*F10*12 -> 24404112 | K10: =C10*G10*12 -> 30680650 | L10: =K10-J10 -> 6276537.6
A11: General Child | B11: 58480 | C11: 55192 | D11: =C11-B11 -> -3288 | E11: =D11/B11 -> -0.05622435 | F11: 285.39 | G11: 329.2 | H11: =G11-F11 -> 43.81 | I11: =H11/F11 -> 0.15350923 | J11: =B11*F11*12 -> 2.0027529e+08 | K11: =C11*G11*12 -> 2.1803048e+08 | L11: =K11-J11 -> 17755190
A12: CHIP | B12: 4411 | C12: 5279 | D12: =C12-B12 -> 868 | E12: =D12/B12 -> 0.19678078 | F12: 184.55 | G12: 227.18 | H12: =G12-F12 -> 42.63 | I12: =H12/F12 -> 0.23099431 | J12: =B12*F12*12 -> 9768600.6 | K12: =C12*G12*12 -> 14391399 | L12: =K12-J12 -> 4622798
A13: Dr. D Expansion (IHIP) | B13: 252 | C13: 415 | D13: =C13-B13 -> 163 | E13: =D13/B13 -> 0.6468254 | F13: 400 | G13: 463.83 | H13: =G13-F13 -> 63.83 | I13: =H13/F13 -> 0.159575 | J13: =B13*F13*12 -> 1209600 | K13: =C13*G13*12 -> 2309873.4 | L13: =K13-J13 -> 1100273.4
A14: Pharmacy Only | B14: 9763 | C14: 9207 | D14: =C14-B14 -> -556 | E14: =D14/B14 -> -0.056949708 | F14: 66.85 | G14: 158.76 | H14: =G14-F14 -> 91.91 | I14: =H14/F14 -> 1.3748691 | J14: =B14*F14*12 -> 7831878.6 | K14: =C14*G14*12 -> 17540440 | L14: =K14-J14 -> 9708561.2
A15: Vermont Premium Assist. | B15: 14165 | C15: 12999 | D15: =C15-B15 -> -1166 | E15: =D15/B15 -> -0.082315567 | F15: 31.85 | G15: 34.61 | H15: =G15-F15 -> 2.76 | I15: =H15/F15 -> 0.086656201 | J15: =B15*F15*12 -> 5413863 | K15: =C15*G15*12 -> 5398744.7 | L15: =K15-J15 -> -15118.32
A16: Vermont Cost Sharing | B16: 4995 | C16: 2175 | D16: =C16-B16 -> -2820 | E16: =D16/B16 -> -0.56456456 | F16: 30.98 | G16: 30.57 | H16: =G16-F16 -> -0.41 | I16: =H16/F16 -> -0.013234345 | J16: =B16*F16*12 -> 1856941.2 | K16: =C16*G16*12 -> 797877 | L16: =K16-J16 -> -1059064.2
A17: TOTALS | B17: =SUM(B5:B16) -> 199751 | C17: =SUM(C5:C16) -> 185704 | D17: =SUM(D5:D16) -> -14047 | E17: — | F17: — | G17: — | H17: — | I17: — | J17: =SUM(J5:J16) -> 8.5107168e+08 | K17: =SUM(K5:K16) -> 9.7626425e+08 | L17: =SUM(L5:L16) -> 1.2519257e+08

Sheet Findings & Resolution Log
A1: Vermont Medicaid SFY2025 — Findings & Resolution Log (Recalibrated Thresholds)
A2: Analyst: Graham Pinti | Items requiring investigation and documented resolution
A3: 18 findings recorded across all 12 of 12 MEGs in this analysis (one row per flagged metric). Using the same recalibrated thresholds applied to SFY2022 (6.3%/9.5% enrollment, 8.9%/13.4% PMPM, derived from historical SFY2020-2024 volatility), every single MEG still flags on at least one metric, unlike SFY2022 where 3 MEGs were fully within normal range. This holds up the central comparative finding: SFY2025's cost-intensity miss is broadly abnormal even under a fair, statistically grounded bar, while SFY2022's apparent crisis was substantially an artifact of an uncalibrated threshold.
A4: MEG | B4: Variance Type | C4: Budget Figure | D4: Actual Figure | E4: Variance | F4: Variance % | G4: Finding & Root Cause | H4: Resolution & Status
A5: ABD Adult | B5: Enrollment | C5: 8005 | D5: 7402 | E5: (603) | F5: (7.53%) | G5: Enrollment came in 7.53% below budget, consistent with the post-unwinding redetermination cycle removing members who no longer qualified once continuous enrollment protections ended. | H5: MONITOR — Enrollment variance under recalibrated threshold (1 stdev = 6.3%, 1.5 stdev = 9.5%). GP 6/29/26
A6: ABD Adult | B6: PMPM Cost | C6: $846.95 | D6: $1171.49 | E6: +$324.54 | F6: +38.32% | G6: PMPM exceeded budget by 38.32%, the largest PMPM variance among the major adult categories. Consistent with DVHA's own documented finding that the population retained after redeterminations ('stayers') skewed costlier on average. Additionally, Vermont's Global Commitment Register shows a documented SFY2025 rate increase for DAIL (Department of Disabilities, Aging, and Independent Living) services, which directly affects this aged/blind/disabled population. Because this rate increase raises payment per service while the retained population is also using more services per person, the two effects compound rather than offset, both push PMPM in the same direction at once. The rate increase's comment period closed in mid-2025, after the As Passed budget was already locked, making this a genuinely unbudgeted addition, not a forecasting oversight. | H6: ESCALATE — PMPM variance under recalibrated threshold (1 stdev = 8.9%, 1.5 stdev = 13.4%). GP 6/29/26
A7: General Adult | B7: Enrollment | C7: 15000 | D7: 12351 | E7: (2649) | F7: (17.66%) | G7: Enrollment came in 17.66% below budget, the largest percentage shortfall among the larger adult categories, consistent with the post-unwinding redetermination cycle removing parents/caretakers whose circumstances changed during the PHE. | H7: ESCALATE — Enrollment variance under recalibrated threshold (1 stdev = 6.3%, 1.5 stdev = 9.5%). GP 6/29/26
A8: General Adult | B8: PMPM Cost | C8: $415.86 | D8: $568.79 | E8: +$152.93 | F8: +36.77% | G8: PMPM exceeded budget by 36.77%, consistent with a costlier retained population following redeterminations. | H8: ESCALATE — PMPM variance under recalibrated threshold (1 stdev = 8.9%, 1.5 stdev = 13.4%). GP 6/29/26
A9: New Adult Childless | B9: Enrollment | C9: 38000 | D9: 35417 | E9: (2583) | F9: (6.80%) | G9: Enrollment came in 6.80% below budget. This category drove the largest single dollar overrun in SFY2022 due to PHE continuous enrollment; the SFY2025 contraction reflects the same population normalizing post-unwinding. | H9: MONITOR — Enrollment variance under recalibrated threshold (1 stdev = 6.3%, 1.5 stdev = 9.5%). GP 6/29/26
A10: New Adult Childless | B10: PMPM Cost | C10: $491.19 | D10: $584.85 | E10: +$93.66 | F10: +19.07% | G10: PMPM exceeded budget by 19.07%, consistent with the statewide 'stayer' cost pattern. | H10: ESCALATE — PMPM variance under recalibrated threshold (1 stdev = 8.9%, 1.5 stdev = 13.4%). GP 6/29/26
A11: BD Child | B11: Enrollment | C11: 1800 | D11: 1928 | E11: 128 | F11: +7.11% | G11: Enrollment exceeded budget by 7.11%, one of the few categories to grow. High-acuity disabled children are less likely to lose eligibility during redetermination since disability status is independently verified, not income-dependent. | H11: MONITOR — Enrollment variance under recalibrated threshold (1 stdev = 6.3%, 1.5 stdev = 9.5%). GP 6/29/26
A12: BD Child | B12: PMPM Cost | C12: $1129.82 | D12: $1326.10 | E12: +$196.28 | F12: +17.37% | G12: PMPM exceeded budget by 17.37%, consistent with rising costs for high-acuity pediatric care. | H12: ESCALATE — PMPM variance under recalibrated threshold (1 stdev = 8.9%, 1.5 stdev = 13.4%). GP 6/29/26
A13: CHIP | B13: Enrollment | C13: 4411 | D13: 5279 | E13: 868 | F13: +19.68% | G13: Enrollment exceeded budget by 19.68%. CHIP eligibility sits at a higher income band than core Medicaid; families who lost core Medicaid eligibility during redetermination may have shifted into CHIP rather than losing coverage entirely. | H13: ESCALATE — Enrollment variance under recalibrated threshold (1 stdev = 6.3%, 1.5 stdev = 9.5%). GP 6/29/26
A14: CHIP | B14: PMPM Cost | C14: $184.55 | D14: $227.18 | E14: +$42.63 | F14: +23.10% | G14: PMPM exceeded budget by 23.10%, consistent with broader pediatric cost growth. | H14: ESCALATE — PMPM variance under recalibrated threshold (1 stdev = 8.9%, 1.5 stdev = 13.4%). GP 6/29/26
A15: Dr. D Expansion (IHIP) | B15: Enrollment | C15: 252 | D15: 415 | E15: 163 | F15: +64.68% | G15: Enrollment exceeded budget by 64.68%, the largest percentage variance in the portfolio. IHIP is a new, small, state-funded program (began July 2022) with no federal eligibility verification system; budget projections for a program with this little operating history carry wide uncertainty. | H15: ESCALATE — Enrollment variance under recalibrated threshold (1 stdev = 6.3%, 1.5 stdev = 9.5%). GP 6/29/26
A16: Dr. D Expansion (IHIP) | B16: PMPM Cost | C16: $400.00 | D16: $463.83 | E16: +$63.83 | F16: +15.96% | G16: PMPM exceeded budget by 15.96%, broadly consistent with the same cost-intensity pattern as the rest of the portfolio. | H16: ESCALATE — PMPM variance under recalibrated threshold (1 stdev = 8.9%, 1.5 stdev = 13.4%). GP 6/29/26
A17: Dual Eligible | B17: PMPM Cost | C17: $366.71 | D17: $440.44 | E17: +$73.73 | F17: +20.11% | G17: PMPM exceeded budget by 20.11%, consistent with the broader 'stayer' cost-intensity pattern seen across nearly every category this fiscal year. Enrollment variance (-1.74%) stayed within the recalibrated monitor range. | H17: ESCALATE — PMPM variance under recalibrated threshold (1 stdev = 8.9%, 1.5 stdev = 13.4%). GP 6/29/26
A18: New Adult w/Child | B18: PMPM Cost | C18: $450.49 | D18: $522.94 | E18: +$72.45 | F18: +16.08% | G18: PMPM exceeded budget by 16.08%, consistent with the broader cost-intensity trend. Enrollment variance (-5.12%) stayed within the recalibrated normal range. | H18: ESCALATE — PMPM variance under recalibrated threshold (1 stdev = 8.9%, 1.5 stdev = 13.4%). GP 6/29/26
A19: General Child | B19: PMPM Cost | C19: $285.39 | D19: $329.20 | E19: +$43.81 | F19: +15.35% | G19: PMPM exceeded budget by 15.35%, consistent with the statewide cost-intensity trend. Enrollment variance (-5.62%) stayed within the recalibrated normal range. | H19: ESCALATE — PMPM variance under recalibrated threshold (1 stdev = 8.9%, 1.5 stdev = 13.4%). GP 6/29/26
A20: Pharmacy Only | B20: PMPM Cost | C20: $66.85 | D20: $158.76 | E20: +$91.91 | F20: +137.49% | G20: PMPM exceeded budget by 137.49%, an order of magnitude larger than any other variance in this analysis and inconsistent with the Budget Book's own BAA/Gov. Rec. trendline for VPharm. The most likely explanation is a gross-vs-net (rebate-adjusted) reporting difference between the two source documents; this could not be confirmed from public data alone. Enrollment variance (-5.69%) stayed within the recalibrated normal range. | H20: ESCALATE — PMPM variance under recalibrated threshold (1 stdev = 8.9%, 1.5 stdev = 13.4%). GP 6/29/26
A21: Vermont Premium Assist. | B21: Enrollment | C21: 14165 | D21: 12999 | E21: (1166) | F21: (8.23%) | G21: Enrollment came in 8.23% below budget, consistent with marketplace enrollment volatility in this QHP-linked population, which is separate from core Medicaid continuous enrollment protections. PMPM variance (+8.67%) stayed within the recalibrated normal range. | H21: MONITOR — Enrollment variance under recalibrated threshold (1 stdev = 6.3%, 1.5 stdev = 9.5%). GP 6/29/26
A22: Vermont Cost Sharing | B22: Enrollment | C22: 4995 | D22: 2175 | E22: (2820) | F22: (56.46%) | G22: Enrollment came in 56.46% below budget, the single largest percentage swing in the analysis. This small QHP-linked population appears to have contracted sharply, consistent with marketplace dynamics affecting the related Premium Assistance category. PMPM variance (-1.32%) was favorable and within the recalibrated normal range. | H22: ESCALATE — Enrollment variance under recalibrated threshold (1 stdev = 6.3%, 1.5 stdev = 9.5%). GP 6/29/26
A23: LEGEND: Red = Unfavorable variance. Green = Favorable variance. Bold rows = the 3 largest cost impacts in the portfolio. All 12 MEGs flag on at least one metric, even under the recalibrated, statistically grounded threshold.

Sheet Summary Dashboard
A1: Vermont Medicaid SFY2025 — Reconciliation Summary Dashboard (Recalibrated Thresholds)
A2: Thresholds: 6.3%/9.5% enrollment, 8.9%/13.4% PMPM (1/1.5 historical stdev) — matched to SFY2022 methodology
A3: RECONCILIATION SUMMARY — SFY2025 (Real Actuals)
A4: Metric | B4: Budget | C4: Actual | D4: Variance
A5: Total MEGs Reviewed | B5: =COUNTA('Reconciliation Report'!A5:A16) -> 12 | C5: =COUNTA('Reconciliation Report'!A5:A16) -> 12 | D5: —
A6: Total Enrolled Members (Avg Monthly) | B6: ='Reconciliation Report'!B17 -> 199751 | C6: ='Reconciliation Report'!C17 -> 185704 | D6: =C6-B6 -> -14047
A7: Total Annual Budget Estimate ($) | B7: ='Reconciliation Report'!J17 -> 8.5107168e+08 | C7: ='Reconciliation Report'!K17 -> 9.7626425e+08 | D7: =C7-B7 -> 1.2519257e+08
A8: MEGs with No Variance | B8: =B5 -> 12 | C8: =COUNTIFS('Reconciliation Report'!E5:E16,"<=0.063",'Reconciliation Report'!E5:E16,">=-0.063",'Reconciliation Report'!I5:I16,"<=0.089",'Reconciliation Report'!I5:I16,">=-0.089") -> 0 | D8: =C8-B8 -> -12
A9: MEGs Flagged for Review | B9: 0 | C9: =C5-C8 -> 12 | D9: =C9-B9 -> 12
A10: MEGs Escalated (>Threshold) | B10: 0 | C10: =SUMPRODUCT((ABS('Reconciliation Report'!E5:E16)>0.095)+(ABS('Reconciliation Report'!I5:I16)>0.134)>0) -> 0 | D10: =C10-B10 -> 0
A11: MEGs Resolved | B11: 0 | C11: =COUNTIF('Findings & Resolution Log'!H5:H22,"RESOLVED*") -> 0 | D11: =C11-B11 -> 0
A13: TOP ESCALATED ITEMS BY COST IMPACT
A14: New Adult Childless | B14: Enrollment -6.80%, PMPM +19.07% — $24,579,122 over budget | C14: Flag under recalibrated threshold: ESCALATE — see Findings Log
A15: ABD Adult | B15: Enrollment -7.53%, PMPM +38.32% — $22,698,067 over budget | C15: Flag under recalibrated threshold: ESCALATE — see Findings Log
A16: General Child | B16: Enrollment -5.62%, PMPM +15.35% — $17,755,825 over budget | C16: Flag under recalibrated threshold: ESCALATE — see Findings Log
A17: DATA SOURCE: Budget — DVHA Annual Report and Budget Book SFY2026 (SFY2025 As Passed, retroactively reported). Actuals — DVHA Medicaid Program Enrollment & Expenditures Quarterly Report, Q4 SFY25 YTD, DVHA-only scope. Thresholds recalibrated from historical SFY2020-2024 year-over-year volatility, matched to SFY2022 methodology. Analysis prepared by Graham Pinti for portfolio demonstration.
A18: COST DRIVER ANALYSIS: SFY2025’s PMPM growth reflects at least three real, distinguishable mechanisms, not a single cause. (1) Population composition shift: DVHA’s own analysis found the population retained after post-PHE redeterminations skewed costlier on average. (2) Legislated provider rate increases: Vermont’s Global Commitment Register documents specific SFY2025 rate increases for DAIL disability services, mobile crisis services, and Department of Mental Health fee-for-service rates, several with comment periods closing mid-2025, after the As Passed budget was locked. Where enrollment also rose for the same population, the rate increase and utilization growth compound rather than offset. (3) General medical inflation: confirmed real but minor (2.5%-4.2% nationally during this period), insufficient alone to explain variances in the 15%-38% range. A fourth factor, newly covered benefits and services added during SFY2025, was identified but not quantified. These mechanisms could not be individually decomposed without category-level claims data.
