Workbook

Sheet SFY2022 Budget Reference
A1: Vermont Medicaid SFY2022 — Budgeted PMPM Reference Data
A2: Source: DVHA Annual PMPM Legislative Report (September 15, 2022) | Prepared by: Patrick Rooney, Financial Director IV
A3: NOTE: This report contains budgetary projections only ("As Passed"). Figures represent projected monthly average enrollment and gross PMPM costs per eligibility group. Premiums paused for Public Health Emergency — Premium PMPM = $0 for all groups. Source data is reproduced verbatim from the official DVHA legislative report.
A4: Medicaid Eligibility Group (MEG) | B4: Avg Monthly Enrollment | C4: Gross PMPM ($) | D4: Premium PMPM ($) | E4: Net PMPM ($) | F4: Annual Budget Est. ($)
A5: ABD Adult | B5: 6475 | C5: 764.19 | D5: 0 | E5: =C5-D5 -> 764.19 | F5: =B5*C5*12 -> 59377563
A6: ABD Dual | B6: 17649 | C6: 257.64 | D6: 0 | E6: =C6-D6 -> 257.64 | F6: =B6*C6*12 -> 54565060
A7: General Adult | B7: 10049 | C7: 502.44 | D7: 0 | E7: =C7-D7 -> 502.44 | F7: =B7*C7*12 -> 60588235
A8: New Adult Childless | B8: 35802 | C8: 470.11 | D8: 0 | E8: =C8-D8 -> 470.11 | F8: =B8*C8*12 -> 2.0197054e+08
A9: New Adult w/Child | B9: 22258 | C9: 404.75 | D9: 0 | E9: =C9-D9 -> 404.75 | F9: =B9*C9*12 -> 108107106
A10: Vermont Premium Assist. | B10: 15937 | C10: 29.36 | D10: 0 | E10: =C10-D10 -> 29.36 | F10: =B10*C10*12 -> 5614923.8
A11: Vermont Cost Sharing | B11: 3236 | C11: 29.12 | D11: 0 | E11: =C11-D11 -> 29.12 | F11: =B11*C11*12 -> 1130787.8
A12: ABD Child | B12: 1594 | C12: 1068.01 | D12: 0 | E12: =C12-D12 -> 1068.01 | F12: =B12*C12*12 -> 20428895
A13: General Child | B13: 59588 | C13: 224.4 | D13: 0 | E13: =C13-D13 -> 224.4 | F13: =B13*C13*12 -> 1.6045857e+08
A14: Underinsured Child | B14: 530 | C14: 68.19 | D14: 0 | E14: =C14-D14 -> 68.19 | F14: =B14*C14*12 -> 433688.4
A15: CHIP | B15: 4374 | C15: 165.45 | D15: 0 | E15: =C15-D15 -> 165.45 | F15: =B15*C15*12 -> 8684139.6
A16: Pharmacy Only | B16: 9568 | C16: 47.5 | D16: 0 | E16: =C16-D16 -> 47.5 | F16: =B16*C16*12 -> 5453760
A17: Choices for Care | B17: 4596 | C17: 727.16 | D17: 0 | E17: =C17-D17 -> 727.16 | F17: =B17*C17*12 -> 40104328
A18: TOTAL / WEIGHTED AVG | B18: =SUM(B5:B17) -> 191656 | C18: =SUMPRODUCT(B5:B17,C5:C17)/SUM(B5:B17) -> 316.06872 | D18: — | E18: =SUMPRODUCT(B5:B17,E5:E17)/SUM(B5:B17) -> 316.06872 | F18: =SUM(F5:F17) -> 7.2691759e+08
A19: Note: Enrollment and Annual Budget are totals (summed). PMPM figures are enrollment-weighted averages, not simple averages.

Sheet Reconciliation Report
A1: Vermont Medicaid SFY2022 — Budget vs. Actual PMPM Reconciliation (Recalibrated Thresholds)
A2: Prepared by: Graham Pinti | Recalibrated Threshold: Monitor >6.3% enroll/8.9% PMPM, Escalate >9.5%/13.4% (1/1.5 historical stdev)
A3: RECONCILIATION PROCESS: Budgeted figures sourced from DVHA SFY2022 Annual PMPM Legislative Report (As Passed budget). Actual figures sourced from the DVHA Medicaid Program Enrollment & Expenditures Quarterly Report, Q4 SFY22 YTD (DVHA-only scope, period ending June 30, 2022). Thresholds were originally set as a flat 1%/2% assumption when this project was first built; that threshold was found to be 4-6x tighter than this system's natural year-over-year volatility (derived from real SFY2020-2024 DVHA data) and has been recalibrated accordingly. Choices for Care actuals reflect the Acute sub-category only; Traditional long-term care is budgeted/administered separately and reports $0 expenditure under DVHA-only scope.
A4: MEG | B4: Budget Enrollment | C4: Actual Enrollment | D4: Enroll. Variance | E4: Enroll. Var % | F4: Budget PMPM ($) | G4: Actual PMPM ($) | H4: PMPM Variance ($) | I4: PMPM Var % | J4: Budget Ann. Cost ($) | K4: Actual Ann. Cost ($) | L4: Cost Impact ($)
A5: ABD Adult | B5: 6475 | C5: 6117 | D5: =C5-B5 -> -358 | E5: =D5/B5 -> -0.055289575 | F5: 764.19 | G5: 832.45 | H5: =G5-F5 -> 68.26 | I5: =H5/F5 -> 0.089323336 | J5: =B5*F5*12 -> 59377563 | K5: =C5*G5*12 -> 61105160 | L5: =K5-J5 -> 1727596.8
A6: ABD Dual | B6: 17649 | C6: 18307 | D6: =C6-B6 -> 658 | E6: =D6/B6 -> 0.037282566 | F6: 257.64 | G6: 233.05 | H6: =G6-F6 -> -24.59 | I6: =H6/F6 -> -0.095443254 | J6: =B6*F6*12 -> 54565060 | K6: =C6*G6*12 -> 51197356 | L6: =K6-J6 -> -3367704.1
A7: General Adult | B7: 10049 | C7: 16159 | D7: =C7-B7 -> 6110 | E7: =D7/B7 -> 0.6080207 | F7: 502.44 | G7: 362.05 | H7: =G7-F7 -> -140.39 | I7: =H7/F7 -> -0.27941645 | J7: =B7*F7*12 -> 60588235 | K7: =C7*G7*12 -> 70204391 | L7: =K7-J7 -> 9616156.7
A8: New Adult Childless | B8: 35802 | C8: 47805 | D8: =C8-B8 -> 12003 | E8: =D8/B8 -> 0.3352606 | F8: 470.11 | G8: 441.97 | H8: =G8-F8 -> -28.14 | I8: =H8/F8 -> -0.059858331 | J8: =B8*F8*12 -> 2.0197054e+08 | K8: =C8*G8*12 -> 2.5354051e+08 | L8: =K8-J8 -> 51569972
A9: New Adult w/Child | B9: 22258 | C9: 25109 | D9: =C9-B9 -> 2851 | E9: =D9/B9 -> 0.12808878 | F9: 404.75 | G9: 437.2 | H9: =G9-F9 -> 32.45 | I9: =H9/F9 -> 0.080172946 | J9: =B9*F9*12 -> 108107106 | K9: =C9*G9*12 -> 1.3173186e+08 | L9: =K9-J9 -> 23624752
A10: Vermont Premium Assist. | B10: 15937 | C10: 12471 | D10: =C10-B10 -> -3466 | E10: =D10/B10 -> -0.21748133 | F10: 29.36 | G10: 30.23 | H10: =G10-F10 -> 0.87 | I10: =H10/F10 -> 0.029632153 | J10: =B10*F10*12 -> 5614923.8 | K10: =C10*G10*12 -> 4523980 | L10: =K10-J10 -> -1090943.9
A11: Vermont Cost Sharing | B11: 3236 | C11: 3041 | D11: =C11-B11 -> -195 | E11: =D11/B11 -> -0.06025958 | F11: 29.12 | G11: 26.99 | H11: =G11-F11 -> -2.13 | I11: =H11/F11 -> -0.073145604 | J11: =B11*F11*12 -> 1130787.8 | K11: =C11*G11*12 -> 984919.08 | L11: =K11-J11 -> -145868.76
A12: ABD Child | B12: 1594 | C12: 1535 | D12: =C12-B12 -> -59 | E12: =D12/B12 -> -0.037013802 | F12: 1068.01 | G12: 1015.84 | H12: =G12-F12 -> -52.17 | I12: =H12/F12 -> -0.048847857 | J12: =B12*F12*12 -> 20428895 | K12: =C12*G12*12 -> 18711773 | L12: =K12-J12 -> -1717122.5
A13: General Child | B13: 59588 | C13: 61833 | D13: =C13-B13 -> 2245 | E13: =D13/B13 -> 0.037675371 | F13: 224.4 | G13: 252.33 | H13: =G13-F13 -> 27.93 | I13: =H13/F13 -> 0.12446524 | J13: =B13*F13*12 -> 1.6045857e+08 | K13: =C13*G13*12 -> 1.8722785e+08 | L13: =K13-J13 -> 26769284
A14: Underinsured Child | B14: 530 | C14: 616 | D14: =C14-B14 -> 86 | E14: =D14/B14 -> 0.16226415 | F14: 68.19 | G14: 68.41 | H14: =G14-F14 -> 0.22 | I14: =H14/F14 -> 0.0032262795 | J14: =B14*F14*12 -> 433688.4 | K14: =C14*G14*12 -> 505686.72 | L14: =K14-J14 -> 71998.32
A15: CHIP | B15: 4374 | C15: 4707 | D15: =C15-B15 -> 333 | E15: =D15/B15 -> 0.076131687 | F15: 165.45 | G15: 175.64 | H15: =G15-F15 -> 10.19 | I15: =H15/F15 -> 0.061589604 | J15: =B15*F15*12 -> 8684139.6 | K15: =C15*G15*12 -> 9920849.8 | L15: =K15-J15 -> 1236710.2
A16: Pharmacy Only | B16: 9568 | C16: 9616 | D16: =C16-B16 -> 48 | E16: =D16/B16 -> 0.0050167224 | F16: 47.5 | G16: 55.4 | H16: =G16-F16 -> 7.9 | I16: =H16/F16 -> 0.16631579 | J16: =B16*F16*12 -> 5453760 | K16: =C16*G16*12 -> 6392716.8 | L16: =K16-J16 -> 938956.8
A17: Choices for Care | B17: 4596 | C17: 4448 | D17: =C17-B17 -> -148 | E17: =D17/B17 -> -0.032201915 | F17: 727.16 | G17: 710.49 | H17: =G17-F17 -> -16.67 | I17: =H17/F17 -> -0.022924803 | J17: =B17*F17*12 -> 40104328 | K17: =C17*G17*12 -> 37923114 | L17: =K17-J17 -> -2181214.1
A18: TOTALS | B18: =SUM(B5:B17) -> 191656 | C18: =SUM(C5:C17) -> 211764 | D18: =SUM(D5:D17) -> 20108 | E18: — | F18: — | G18: — | H18: — | I18: — | J18: =SUM(J5:J17) -> 7.2691759e+08 | K18: =SUM(K5:K17) -> 8.3397017e+08 | L18: =SUM(L5:L17) -> 1.0705257e+08
A19: Note: Bold rows indicate the 3 largest cost impacts in the portfolio (New Adult Childless, General Child, New Adult w/Child).

Sheet Findings & Resolution Log
A1: Vermont Medicaid SFY2022 — Findings & Resolution Log (Recalibrated Thresholds)
A2: Analyst: Graham Pinti | Items requiring investigation and documented resolution
A3: 11 findings recorded across 10 of 13 MEGs in this analysis (one row per flagged metric). Thresholds were recalibrated from an original flat 1%/2% assumption to 6.3%/9.5% (enrollment) and 8.9%/13.4% (PMPM), based on historical year-over-year actual volatility by MEG (SFY2020-2024 DVHA data). The original thresholds were 4-6x tighter than this system's natural background noise, which is why the uncalibrated version flagged nearly every MEG regardless of real abnormality. Under the recalibrated threshold, 3 MEGs (ABD Child, Choices for Care, Vermont Cost Sharing) are fully within normal range, and General Adult is the only MEG flagging on both metrics.
A4: MEG | B4: Variance Type | C4: Budget Figure | D4: Actual Figure | E4: Variance | F4: Variance % | G4: Finding & Root Cause | H4: Resolution & Status
A5: ABD Adult | B5: PMPM Cost | C5: $764.19 | D5: $832.45 | E5: +$68.26 | F5: +8.93% | G5: PMPM exceeded budget by 8.93%, consistent with pent-up demand for delayed elective and specialty care as providers resumed normal operations following pandemic-era deferrals. | H5: MONITOR — PMPM variance exceeds recalibrated threshold (1 stdev = 8.9%, 1.5 stdev = 13.4%). GP 6/29/26
A6: ABD Dual | B6: PMPM Cost | C6: $257.64 | D6: $233.05 | E6: ($24.59) | F6: (9.54%) | G6: PMPM came in 9.54% under budget. Medicare-as-primary-payer for this dual-eligible population likely absorbed a larger share of cost growth, holding Medicaid-side PMPM down despite a modest enrollment increase. | H6: MONITOR — PMPM variance exceeds recalibrated threshold (1 stdev = 8.9%, 1.5 stdev = 13.4%). GP 6/29/26
A7: General Adult | B7: Enrollment | C7: 10049 | D7: 16159 | E7: 6110 | F7: +60.80% | G7: Enrollment exceeded budget by 60.80%, the largest variance in the portfolio and the only MEG flagging on both metrics even under the recalibrated threshold. Driven by federal PHE continuous enrollment provisions barring disenrollment of parents/caretakers and transitional Medicaid recipients throughout SFY22. | H7: ESCALATE — Enrollment variance exceeds recalibrated threshold (1 stdev = 6.3%, 1.5 stdev = 9.5%). GP 6/29/26
A8: General Adult | B8: PMPM Cost | C8: $502.44 | D8: $362.05 | E8: ($140.39) | F8: (27.94%) | G8: PMPM dropped 27.94% below budget as the retained population included many lower-acuity members who would otherwise have cycled off, diluting average per-member cost. | H8: ESCALATE — PMPM variance exceeds recalibrated threshold (1 stdev = 8.9%, 1.5 stdev = 13.4%). GP 6/29/26
A9: New Adult Childless | B9: Enrollment | C9: 35802 | D9: 47805 | E9: 12003 | F9: +33.53% | G9: Enrollment exceeded budget by 33.53%, consistent with the statewide PHE continuous enrollment effect across expansion adult categories. | H9: ESCALATE — Enrollment variance exceeds recalibrated threshold (1 stdev = 6.3%, 1.5 stdev = 9.5%). GP 6/29/26
A10: New Adult w/Child | B10: Enrollment | C10: 22258 | D10: 25109 | E10: 2851 | F10: +12.81% | G10: Enrollment exceeded budget by 12.81%, driven by PHE continuous enrollment protections applying to parents with dependent children. | H10: ESCALATE — Enrollment variance exceeds recalibrated threshold (1 stdev = 6.3%, 1.5 stdev = 9.5%). GP 6/29/26
A11: General Child | B11: PMPM Cost | C11: $224.40 | D11: $252.33 | E11: +$27.93 | F11: +12.45% | G11: PMPM exceeded budget by 12.45%, consistent with a statewide rebound in pediatric care utilization, including catch-up well-child visits and vaccinations deferred earlier in the pandemic. | H11: MONITOR — PMPM variance exceeds recalibrated threshold (1 stdev = 8.9%, 1.5 stdev = 13.4%). GP 6/29/26
A12: Underinsured Child | B12: Enrollment | C12: 530 | D12: 616 | E12: 86 | F12: +16.23% | G12: Enrollment exceeded budget by 16.23%. This is a small population, so percentage swings are naturally amplified by a modest absolute change. Likely reflects economic disruption during the pandemic recovery period increasing reliance on wraparound coverage for children with other primary insurance. | H12: ESCALATE — Enrollment variance exceeds recalibrated threshold (1 stdev = 6.3%, 1.5 stdev = 9.5%). GP 6/29/26
A13: CHIP | B13: Enrollment | C13: 4374 | D13: 4707 | E13: 333 | F13: +7.61% | G13: Enrollment exceeded budget by 7.61% as continuous enrollment provisions applied to CHIP families as well as core Medicaid categories. | H13: MONITOR — Enrollment variance exceeds recalibrated threshold (1 stdev = 6.3%, 1.5 stdev = 9.5%). GP 6/29/26
A14: Pharmacy Only | B14: PMPM Cost | C14: $47.50 | D14: $55.40 | E14: +$7.90 | F14: +16.63% | G14: PMPM exceeded budget by 16.63%, the largest percentage cost overrun in the portfolio. Consistent with statewide pharmacy spend trends in SFY22 driven by specialty drug cost growth and rising prescription volume as members resumed regular prescribing patterns post-pandemic. | H14: ESCALATE — PMPM variance exceeds recalibrated threshold (1 stdev = 8.9%, 1.5 stdev = 13.4%). GP 6/29/26
A15: Vermont Premium Assist. | B15: Enrollment | C15: 15937 | D15: 12471 | E15: (3466) | F15: (21.75%) | G15: Enrollment fell 21.75% below budget, the only large category to decline meaningfully. This population draws from the QHP marketplace rather than core Medicaid, so it was not protected by continuous enrollment; the drop is consistent with members shifting to employer-sponsored coverage as the labor market recovered. | H15: ESCALATE — Enrollment variance exceeds recalibrated threshold (1 stdev = 6.3%, 1.5 stdev = 9.5%). GP 6/29/26

Sheet Summary Dashboard
A1: Vermont Medicaid SFY2022 — Reconciliation Summary Dashboard (Recalibrated Thresholds)
A2: Thresholds: 6.3%/9.5% enrollment, 8.9%/13.4% PMPM (1/1.5 historical stdev)
A3: RECONCILIATION SUMMARY — SFY2022 (Real Actuals)
A4: Metric | B4: Budget | C4: Actual | D4: Variance
A5: Total MEGs Reviewed | B5: =COUNTA('Reconciliation Report'!A5:A17) -> 13 | C5: =COUNTA('Reconciliation Report'!A5:A17) -> 13 | D5: —
A6: Total Enrolled Members (Avg Monthly) | B6: ='Reconciliation Report'!B18 -> 191656 | C6: ='Reconciliation Report'!C18 -> 211764 | D6: =C6-B6 -> 20108
A7: Total Annual Budget Estimate ($) | B7: ='Reconciliation Report'!J18 -> 7.2691759e+08 | C7: ='Reconciliation Report'!K18 -> 8.3397017e+08 | D7: =C7-B7 -> 1.0705257e+08
A8: MEGs with No Variance | B8: =B5 -> 13 | C8: =COUNTIFS('Reconciliation Report'!E5:E17,"<=0.063",'Reconciliation Report'!E5:E17,">=-0.063",'Reconciliation Report'!I5:I17,"<=0.089",'Reconciliation Report'!I5:I17,">=-0.089") -> 3 | D8: =C8-B8 -> -10
A9: MEGs Flagged for Review | B9: 0 | C9: =C5-C8 -> 10 | D9: =C9-B9 -> 10
A10: MEGs Escalated (>Threshold) | B10: 0 | C10: =SUMPRODUCT((ABS('Reconciliation Report'!E5:E17)>0.095)+(ABS('Reconciliation Report'!I5:I17)>0.134)>0) -> 0 | D10: =C10-B10 -> 0
A11: MEGs Resolved | B11: 0 | C11: =COUNTIF('Findings & Resolution Log'!H5:H15,"RESOLVED*") -> 0 | D11: =C11-B11 -> 0
A13: TOP ESCALATED ITEMS BY COST IMPACT
A14: New Adult Childless | B14: Enrollment +33.53%, PMPM -5.99% — $51,569,972 over budget | C14: Flag under recalibrated threshold: ESCALATE — see Findings Log
A15: General Child | B15: Enrollment +3.77%, PMPM +12.45% — $26,769,284 over budget | C15: Flag under recalibrated threshold: MONITOR — see Findings Log
A16: New Adult w/Child | B16: Enrollment +12.81%, PMPM +8.02% — $23,624,752 over budget | C16: Flag under recalibrated threshold: ESCALATE — see Findings Log
A17: DATA SOURCE: Budget — DVHA SFY2022 Annual PMPM Legislative Report (As Passed). Actuals — DVHA Medicaid Program Enrollment & Expenditures Quarterly Report, Q4 SFY22 YTD, DVHA-only scope. Thresholds recalibrated from historical SFY2020-2024 year-over-year volatility. Analysis prepared by Graham Pinti for portfolio demonstration.
A18: COST DRIVER ANALYSIS: SFY2022's variances reflect a single dominant mechanism, not several compounding factors. (1) Federal PHE continuous enrollment: under the Families First Coronavirus Response Act, states could not disenroll Medicaid members for the duration of the COVID-19 public health emergency. This froze three years of normal eligibility-review churn, driving enrollment well above budget in nearly every adult and family category (General Adult +60.8%, the largest single variance in this analysis). (2) PMPM moved in mixed directions depending on category, not a uniform cost-intensity rise. Several categories show a dilution effect: the retained population included many lower-acuity members who would normally have cycled off, pulling average PMPM down even as enrollment rose (General Adult PMPM -27.94%, New Adult Childless -5.99%). Other categories show the opposite, a utilization rebound as deferred pandemic-era care resumed (ABD Adult PMPM +8.93%, General Child +12.45%). Unlike SFY2025, no specific provider rate increases or other documented cost-side policy actions were identified for this period; the enrollment effect alone accounts for the majority of this year's variance. See the SFY2025 companion analysis for a contrasting year driven primarily by cost intensity rather than enrollment volume.
